ps2.v
`timescale 1ns / 1ns

module ps2(input clk_i, input rst_i, input ps2_clk_i, input ps2_data_i, output reg [3:0] digit_o, output reg new_data_o);
    function [3:0] ps2_conv;
        input [7:0] code_i;

        case(code_i)
            8'h45: ps2_conv = 4'd0;
            8'h16: ps2_conv = 4'd1;
            8'h1e: ps2_conv = 4'd2;
            8'h26: ps2_conv = 4'd3;
            8'h25: ps2_conv = 4'd4;
            8'h23: ps2_conv = 4'd5;
            8'h36: ps2_conv = 4'd6;
            8'h3d: ps2_conv = 4'd7;
            8'h3e: ps2_conv = 4'd8;
            8'h46: ps2_conv = 4'd9;
            8'h7b: ps2_conv = 4'd10;
            8'h79: ps2_conv = 4'd11;
            8'h55: ps2_conv = 4'd12;
            8'h76: ps2_conv = 4'd13;
            default: ps2_conv = 4'd0;
        endcase
    endfunction

    reg [4:0] counter;

    reg [7:0] digit;
    wire [6:0] digit_sft = digit >> 1;

    reg prev_ps2_clk, curr_ps2_clk;

    always @(posedge clk_i, posedge rst_i) begin
        if(rst_i) begin
            counter <= 0;
            digit <= 0;
            digit_o <= 0;
            prev_ps2_clk <= 0;
            curr_ps2_clk <= 0;
            new_data_o <= 0;
        end
        else if(clk_i) begin
            prev_ps2_clk <= curr_ps2_clk;
            curr_ps2_clk <= ps2_clk_i;

            new_data_o <= 0;

            if(prev_ps2_clk == 1 && curr_ps2_clk == 0) begin
                if(counter >= 10) begin
                    counter <= 0;
                    digit_o <= ps2_conv(digit);
                    new_data_o <= 1;
                end
                else begin
                    counter <= counter + 1;

                    if(counter == 0) begin
                        digit <= 0;
                    end
                    else if(counter >= 1 && counter <= 8) begin
                        digit <= {ps2_data_i, digit_sft};
                    end
                end
            end
        end
    end
endmodule

ps2_tb.v
`timescale 1ns / 1ns
`include "ps2.v"

module ps2_tb;
    reg clk_i, rst_i, ps2_clk_i, ps2_data_i;
    wire [3:0] digit_o;

    wire new_data_o;

    ps2 uut(clk_i, rst_i, ps2_clk_i, ps2_data_i, digit_o, new_data_o);

    initial begin
        $dumpfile("ps2_tb.vcd");
        $dumpvars(0, clk_i, rst_i, ps2_clk_i, ps2_data_i, digit_o, new_data_o);

        clk_i = 0;
        rst_i = 0;
        ps2_clk_i = 1;
        ps2_data_i = 0;

        #1  rst_i = 1;
        #1  rst_i = 0;

        #5  ps2_clk_i = 1;
            ps2_data_i = 0;
        #5  ps2_clk_i = 0;

        #5  ps2_clk_i = 1;
            ps2_data_i = 0;
        #5  ps2_clk_i = 0;

        #5  ps2_clk_i = 1;
            ps2_data_i = 0;
        #5  ps2_clk_i = 0;

        #5  ps2_clk_i = 1;
            ps2_data_i = 1;
        #5  ps2_clk_i = 0;

        #5  ps2_clk_i = 1;
            ps2_data_i = 1;
        #5  ps2_clk_i = 0;

        #5  ps2_clk_i = 1;
            ps2_data_i = 0;
        #5  ps2_clk_i = 0;

        #5  ps2_clk_i = 1;
            ps2_data_i = 1;
        #5  ps2_clk_i = 0;

        #5  ps2_clk_i = 1;
            ps2_data_i = 1;
        #5  ps2_clk_i = 0;

        #5  ps2_clk_i = 1;
            ps2_data_i = 0;
        #5  ps2_clk_i = 0;

        #5  ps2_clk_i = 1;
            ps2_data_i = 0;
        #5  ps2_clk_i = 0;

        #5  ps2_clk_i = 1;
            ps2_data_i = 1;
        #5  ps2_clk_i = 0;

        #500

        #5  ps2_clk_i = 1;
            ps2_data_i = 0;
        #5  ps2_clk_i = 0;

        #5  ps2_clk_i = 1;
            ps2_data_i = 0;
        #5  ps2_clk_i = 0;

        #5  ps2_clk_i = 1;
            ps2_data_i = 1;
        #5  ps2_clk_i = 0;

        #5  ps2_clk_i = 1;
            ps2_data_i = 0;
        #5  ps2_clk_i = 0;

        #5  ps2_clk_i = 1;
            ps2_data_i = 1;
        #5  ps2_clk_i = 0;

        #5  ps2_clk_i = 1;
            ps2_data_i = 0;
        #5  ps2_clk_i = 0;

        #5  ps2_clk_i = 1;
            ps2_data_i = 1;
        #5  ps2_clk_i = 0;

        #5  ps2_clk_i = 1;
            ps2_data_i = 0;
        #5  ps2_clk_i = 0;

        #5  ps2_clk_i = 1;
            ps2_data_i = 1;
        #5  ps2_clk_i = 0;

        #5  ps2_clk_i = 1;
            ps2_data_i = 0;
        #5  ps2_clk_i = 0;

        #5  ps2_clk_i = 1;
            ps2_data_i = 1;
        #5  ps2_clk_i = 0;

        #5  ps2_clk_i = 1;

        #200 $finish;
    end

    always #1 clk_i = ~clk_i;
endmodule

ps2_tb.vcd
$date
	Wed Mar 13 14:48:31 2024
$end
$version
	Icarus Verilog
$end
$timescale
	1ns
$end
$scope module ps2_tb $end
$var reg 1 ! clk_i $end
$upscope $end
$scope module ps2_tb $end
$var reg 1 " rst_i $end
$upscope $end
$scope module ps2_tb $end
$var reg 1 # ps2_clk_i $end
$upscope $end
$scope module ps2_tb $end
$var reg 1 $ ps2_data_i $end
$upscope $end
$scope module ps2_tb $end
$var wire 4 % digit_o [3:0] $end
$upscope $end
$scope module ps2_tb $end
$var wire 1 & new_data_o $end
$upscope $end
$enddefinitions $end
$comment Show the parameter values. $end
$dumpall
$end
#0
$dumpvars
x&
bx %
0$
1#
0"
0!
$end
#1
0&
b0 %
1!
1"
#2
0!
0"
#3
1!
#4
0!
#5
1!
#6
0!
#7
1!
#8
0!
#9
1!
#10
0!
#11
1!
#12
0!
0#
#13
1!
#14
0!
#15
1!
#16
0!
#17
1!
1#
#18
0!
#19
1!
#20
0!
#21
1!
#22
0!
0#
#23
1!
#24
0!
#25
1!
#26
0!
#27
1!
1#
#28
0!
#29
1!
#30
0!
#31
1!
#32
0!
0#
#33
1!
#34
0!
#35
1!
#36
0!
#37
1!
1$
1#
#38
0!
#39
1!
#40
0!
#41
1!
#42
0!
0#
#43
1!
#44
0!
#45
1!
#46
0!
#47
1!
1#
#48
0!
#49
1!
#50
0!
#51
1!
#52
0!
0#
#53
1!
#54
0!
#55
1!
#56
0!
#57
1!
0$
1#
#58
0!
#59
1!
#60
0!
#61
1!
#62
0!
0#
#63
1!
#64
0!
#65
1!
#66
0!
#67
1!
1$
1#
#68
0!
#69
1!
#70
0!
#71
1!
#72
0!
0#
#73
1!
#74
0!
#75
1!
#76
0!
#77
1!
1#
#78
0!
#79
1!
#80
0!
#81
1!
#82
0!
0#
#83
1!
#84
0!
#85
1!
#86
0!
#87
1!
0$
1#
#88
0!
#89
1!
#90
0!
#91
1!
#92
0!
0#
#93
1!
#94
0!
#95
1!
#96
0!
#97
1!
1#
#98
0!
#99
1!
#100
0!
#101
1!
#102
0!
0#
#103
1!
#104
0!
#105
1!
#106
0!
#107
1!
1$
1#
#108
0!
#109
1!
#110
0!
#111
1!
#112
0!
0#
#113
1!
#114
0!
#115
1&
1!
#116
0!
#117
0&
1!
