ps2.v
`timescale 1ns / 1ns

module ps2(input clk_i, input rst_i, input ps2_clk_i, input ps2_data_i, output reg [3:0] digit_o);
    function [3:0] ps2_conv;
        input [7:0] code_i;

        case(code_i)
            8'h45: ps2_conv = 4'd0;
            8'h16: ps2_conv = 4'd1;
            8'h1e: ps2_conv = 4'd2;
            8'h26: ps2_conv = 4'd3;
            8'h25: ps2_conv = 4'd4;
            8'h23: ps2_conv = 4'd5;
            8'h36: ps2_conv = 4'd6;
            8'h3d: ps2_conv = 4'd7;
            8'h3e: ps2_conv = 4'd8;
            8'h46: ps2_conv = 4'd9;
            default: ps2_conv = 4'd0;
        endcase
    endfunction

    reg [4:0] counter;

    reg [7:0] digit;

    reg prev_ps2_clk, curr_ps2_clk;

    initial begin
        $dumpfile("ps2_tb.vcd");
        $dumpvars(0, prev_ps2_clk, curr_ps2_clk, digit, digit_o);
    end

    always @(posedge clk_i, posedge rst_i) begin

        if(rst_i) begin
            counter <= 0;
            digit <= 0;
            prev_ps2_clk <= 0;
            curr_ps2_clk <= 0;
        end
        else if(clk_i) begin
            prev_ps2_clk <= curr_ps2_clk;
            curr_ps2_clk <= ps2_clk_i;

            if(prev_ps2_clk == 1 && curr_ps2_clk == 0) begin
                if(counter >= 10) begin
                    counter <= 0;
                    digit_o <= ps2_conv(digit);
                end
                else begin
                    counter <= counter + 1;

                    if(counter == 1) begin
                        digit <= 0;
                    end
                    else if(counter >= 1 && counter <= 8) begin
                        digit <= (digit << 1) | ps2_data_i;
                    end
                end
            end
        end
    end
endmodule

bcd_subtractor.v
`timescale 1ns / 1ns

module bcd_subtractor(input [3:0] a_i, input [3:0] b_i, output reg [3:0] diff_o, input borrow_i, output reg borrow_o);
    always @* begin
        if(a_i >= b_i + borrow_i) begin
            diff_o <= a_i - b_i - borrow_i;
            borrow_o <= 0;
        end
        else begin
            diff_o <= a_i - b_i - borrow_i + 5'd10;
            borrow_o <= 1;
        end      
    end
endmodule

bcd_adder.v
`timescale 1ns / 1ns

module bcd_adder(input [3:0] a_i, input [3:0] b_i, output reg [3:0] sum_o, input carry_i, output reg carry_o);
    always @* begin
        if(a_i + b_i + carry_i < 10) begin
            sum_o <= a_i + b_i + carry_i;
            carry_o <= 0;
        end
        else begin
            sum_o <= a_i + b_i + carry_i - 5'd10;
            carry_o <= 1;      
        end
    end
endmodule

display.v
`timescale 1ns / 1ns

module display(input clk_i, input rst_i, 
               input [3:0] dig1000_i, input [3:0] dig100_i, input [3:0] dig10_i, input [3:0] dig1_i,
               output reg [7:0] led7_seg_o, output reg [7:0] led7_an_o);
    function [7:0] seg_char;
        input [3:0] data;
        begin
            case (data)
                4'b0000 : seg_char = 8'b0000_0011;   // 0
                4'b0001 : seg_char = 8'b1001_1111;   // 1
                4'b0010 : seg_char = 8'b0010_0101;   // 2
                4'b0011 : seg_char = 8'b0000_1101;   // 3
                4'b0100 : seg_char = 8'b1001_1001;   // 4
                4'b0101 : seg_char = 8'b0100_1001;   // 5
                4'b0110 : seg_char = 8'b0100_0001;   // 6
                4'b0111 : seg_char = 8'b0001_1111;   // 7
                4'b1000 : seg_char = 8'b0000_0001;   // 8
                4'b1001 : seg_char = 8'b0000_1001;   // 9
                4'b1010 : seg_char = 8'b0001_0001;   // A
                4'b1011 : seg_char = 8'b1100_0001;   // B
                4'b1100 : seg_char = 8'b0110_0011;   // C
                4'b1101 : seg_char = 8'b1000_0101;   // D
                4'b1110 : seg_char = 8'b0110_0001;   // E
                4'b1111 : seg_char = 8'b0111_0001;   // F
                default : seg_char = 8'b1111_1111;   // *blank*
            endcase
        end
    endfunction

    reg [2:0] digit;
    
    always @(posedge clk_i, posedge rst_i) begin
        if(rst_i) begin
            digit <= 0;
            led7_seg_o <= 8'b11111111;
            led7_an_o <= 8'b11111110;
        end
        else if(clk_i) begin
            if(digit >= 7)
                digit <= 0;
            else
                digit <= digit + 1;

            led7_an_o <= ~(1 << digit);

            case(digit)
                0: led7_seg_o <= seg_char(dig1_i);
                1: led7_seg_o <= seg_char(dig10_i);
                2: led7_seg_o <= seg_char(dig100_i);
                3: led7_seg_o <= seg_char(dig1000_i);
                4: led7_seg_o <= 8'b11111111;
                5: led7_seg_o <= 8'b11111111;
                6: led7_seg_o <= 8'b11111111;
                7: led7_seg_o <= 8'b11111111;
            endcase
        end
    end
endmodule

top.v
`timescale 1ns / 1ns
`include "display.v"
`include "ps2.v"
`include "bcd_adder.v"
`include "bcd_subtractor.v"

module top(input clk_i, input rst_i, input ps2_clk_i, input ps2_data_i, 
           output [7:0] led7_seg_o, output [7:0] led7_an_o);

    reg [3:0] dig1, dig10, dig100, dig1000;
    display disp(clk_i, rst_i, dig1, dig10, dig100, dig1000, led7_seg_o, led7_an_o);

    reg [3:0] a1, a10, a100, a1000;
    reg [3:0] b1, b10, b100, b1000;

    wire [3:0] sum1, sum10, sum100, sum1000;
    wire carry1, carry10, carry100, carry1000;

    wire [3:0] diff1, diff10, diff100, diff1000;
    wire borrow1, borrow10, borrow100;

    bcd_adder adder1(a1, b1, sum1, 1'b0, carry1);
    bcd_adder adder10(a10, b10, sum10, carry1, carry10);
    bcd_adder adder100(a100, b100, sum100, carry10, carry100);
    bcd_adder adder1000(a1000, b1000, sum1000, carry100, carry1000);

    bcd_subtractor subtractor1(a1, b1, diff1, 1'b0, borrow1);
    bcd_subtractor subtractor10(a10, b10, diff10, borrow1, borrow10);
    bcd_subtractor subtractor100(a100, b100, diff100, borrow10, borrow100);
    bcd_subtractor subtractor1000(a1000, b1000, diff1000, borrow100, borrow1000);

    wire [3:0] digit_o;
    wire new_data_o;

    ps2 keyboard(clk_i, rst_i, ps2_clk_i, ps2_data_i, digit_o, new_data_o);

    reg [1:0] stage;
    reg add_sub;

    always @(posedge clk_i, posedge rst_i) begin
        if(rst_i) begin
            a1 <= 0;
            a10 <= 0;
            a100 <= 0;
            a1000 <= 0;

            b1 <= 0;
            b10 <= 0;
            b100 <= 0;
            b1000 <= 0;

            stage <= 0;
        end
        else if(clk_i && new_data_o) begin
            if(digit_o < 10 && stage == 2'b00) begin
                a1000 <= a100;
                a100 <= a10;
                a10 <= a1;
                a1 <= digit_o;
            end
            else if(digit_o < 10 && stage == 2'b01) begin
                b1000 <= b100;
                b100 <= a10;
                a10 <= b1;
                b1 <= digit_o;
            end
            else if(digit_o == 10 && stage == 2'b00) begin
                stage <= 2'b01;
                add_sub <= 1;
            end
            else if(digit_o == 11) begin
                stage <= 2'b01;
                add_sub <= 0;
            end
            else if(digit_o == 12) begin
                stage <= 2'b10;
            end
            else if(digit_o == 13) begin
                a1 <= 0;
                a10 <= 0;
                a100 <= 0;
                a1000 <= 0;

                b1 <= 0;
                b10 <= 0;
                b100 <= 0;
                b1000 <= 0;

                stage <= 0;
            end
            else begin

            end
        end
    end

    always @* begin
        case(stage)
            2'b00: begin
                dig1 <= a1;
                dig10 <= a10;
                dig100 <= a100;
                dig1000 <= a1000;
            end
            2'b01: begin
                dig1 <= b1;
                dig10 <= b10;
                dig100 <= b100;
                dig1000 <= b1000;
            end
            2'b10: begin
                if(add_sub) begin
                    dig1 <= sum1;
                    dig10 <= sum10;
                    dig100 <= sum100;
                    dig1000 <= sum1000;
                end
                else begin
                    dig1 <= diff1;
                    dig10 <= diff10;
                    dig100 <= diff100;
                    dig1000 <= diff1000;
                end
            end
            default: begin
                dig1 <= 0;
                dig10 <= 0;
                dig100 <= 0;
                dig1000 <= 0;
            end
        endcase
    end

endmodule

top_tb.v
`timescale 1ns / 1ns
`include "top.v"

module top_tb;
    reg clk_i, rst_i, ps2_clk_i, ps2_data_i;
    wire [7:0] led7_seg_o, led7_an_o;

    top uut(clk_i, rst_i, ps2_clk_i, ps2_data_i, led7_seg_o, led7_an_o);

    task tx;
        input [7:0] key;

        begin
            ps2_clk_i = 1;
            ps2_data_i = 0;

            #5  ps2_clk_i = 1;
                ps2_data_i = 0;
            #5  ps2_clk_i = 0;;

            for(integer i = 0; i < 8; i = i + 1) begin
                #5  ps2_clk_i = 1;
                    ps2_data_i = key[i];
                #5  ps2_clk_i = 0;
            end

            #5  ps2_clk_i = 1;
                ps2_data_i = ^key;
            #5  ps2_clk_i = 0;

            #5  ps2_clk_i = 1;
                ps2_data_i = 1;
            #5  ps2_clk_i = 0;

            #5  ps2_clk_i = 1;
        end
    endtask

    initial begin
        $dumpfile("top_tb.vcd");
        $dumpvars(0, clk_i, rst_i, ps2_clk_i, ps2_data_i, led7_an_o, led7_seg_o, uut.dig1, uut.dig10, uut.dig100, uut.dig1000);

        clk_i = 0;
        rst_i = 0;
        ps2_clk_i = 1;
        ps2_data_i = 0;

        #1  rst_i = 1;
        #1  rst_i = 0;

        tx(8'h46);
        #100
        tx(8'h46);
        #100
        tx(8'h16);

        #100
        tx(8'h7B);

        #100
        tx(8'h16);
        #100
        tx(8'h1e);
        #100
        tx(8'h26);

        #100
        tx(8'h55);

        #100
        tx(8'h76);

        #100
        tx(8'h46);
        #100
        tx(8'h46);
        #100
        tx(8'h16);

        #100
        tx(8'h79);

        #100
        tx(8'h16);
        #100
        tx(8'h1e);
        #100
        tx(8'h26);

        #100
        tx(8'h55);

        #100
        tx(8'h76);

        #200 $finish;
    end

    always #1 clk_i = ~clk_i;
endmodule

top_tb.vcd
$date
	Wed Mar 13 14:57:28 2024
$end
$version
	Icarus Verilog
$end
$timescale
	1ns
$end
$scope module top_tb $end
$var reg 1 ! clk_i $end
$upscope $end
$scope module top_tb $end
$var reg 1 " rst_i $end
$upscope $end
$scope module top_tb $end
$var reg 1 # ps2_clk_i $end
$upscope $end
$scope module top_tb $end
$var reg 1 $ ps2_data_i $end
$upscope $end
$scope module top_tb $end
$var wire 8 % led7_an_o [7:0] $end
$upscope $end
$scope module top_tb $end
$var wire 8 & led7_seg_o [7:0] $end
$upscope $end
$scope module top_tb $end
$scope module uut $end
$var reg 4 ' dig1 [3:0] $end
$upscope $end
$upscope $end
$scope module top_tb $end
$scope module uut $end
$var reg 4 ( dig10 [3:0] $end
$upscope $end
$upscope $end
$scope module top_tb $end
$scope module uut $end
$var reg 4 ) dig100 [3:0] $end
$upscope $end
$upscope $end
$scope module top_tb $end
$scope module uut $end
$var reg 4 * dig1000 [3:0] $end
$upscope $end
$upscope $end
$enddefinitions $end
$comment Show the parameter values. $end
$dumpall
$end
#0
$dumpvars
bx *
bx )
bx (
bx '
bx &
bx %
0$
1#
0"
0!
$end
#1
b11111110 %
b11111111 &
1!
1"
#2
0!
0"
#3
1!
#4
0!
#5
b11111101 %
1!
#6
0!
#7
b11111011 %
1!
#8
0!
#9
b11110111 %
1!
#10
0!
#11
b11101111 %
1!
#12
0!
0#
#13
b11011111 %
1!
#14
0!
#15
b10111111 %
1!
#16
0!
#17
b1111111 %
1!
1#
#18
0!
#19
b11111110 %
1!
#20
0!
#21
b11111101 %
1!
#22
0!
0#
#23
b11111011 %
1!
#24
0!
#25
b11110111 %
1!
#26
0!
#27
b11101111 %
1!
1$
1#
#28
0!
#29
b11011111 %
1!
#30
0!
#31
b10111111 %
1!
#32
0!
0#
#33
b1111111 %
1!
#34
0!
#35
b11111110 %
1!
#36
0!
#37
b11111101 %
1!
1#
#38
0!
#39
b11111011 %
1!
#40
0!
#41
b11110111 %
1!
#42
0!
0#
#43
b11101111 %
1!
#44
0!
#45
b11011111 %
1!
#46
0!
#47
b10111111 %
1!
0$
1#
#48
0!
#49
b1111111 %
1!
#50
0!
#51
b11111110 %
1!
#52
0!
0#
#53
b11111101 %
1!
#54
0!
#55
b11111011 %
1!
#56
0!
#57
b11110111 %
1!
1#
#58
0!
#59
b11101111 %
1!
#60
0!
#61
b11011111 %
1!
#62
0!
0#
#63
b10111111 %
1!
#64
0!
#65
b1111111 %
1!
#66
0!
#67
b11111110 %
1!
1#
#68
0!
#69
b11111101 %
1!
#70
0!
#71
b11111011 %
1!
#72
0!
0#
#73
b11110111 %
1!
#74
0!
#75
b11101111 %
1!
#76
0!
#77
b11011111 %
1!
1$
1#
#78
0!
#79
b10111111 %
1!
#80
0!
#81
b1111111 %
1!
#82
0!
0#
#83
b11111110 %
1!
#84
0!
#85
b11111101 %
1!
#86
0!
#87
b11111011 %
1!
0$
1#
#88
0!
#89
b11110111 %
1!
#90
0!
#91
b11101111 %
1!
#92
0!
0#
#93
b11011111 %
1!
#94
0!
#95
b10111111 %
1!
#96
0!
#97
b1111111 %
1!
1$
1#
#98
0!
#99
b11111110 %
1!
#100
0!
#101
b11111101 %
1!
#102
0!
0#
#103
b11111011 %
1!
#104
0!
#105
b11110111 %
1!
#106
0!
#107
b11101111 %
1!
1#
#108
0!
#109
b11011111 %
1!
#110
0!
#111
b10111111 %
1!
#112
0!
0#
#113
b1111111 %
1!
#114
0!
#115
b11111110 %
1!
#116
0!
#117
b11111101 %
b1001 '
b0 (
b0 )
b0 *
1!
1#
#118
0!
#119
b11 &
b11111011 %
1!
#120
0!
#121
b1001 &
b11110111 %
1!
#122
0!
#123
b11111111 &
b11101111 %
1!
#124
0!
#125
b11011111 %
1!
#126
0!
#127
b10111111 %
1!
#128
0!
#129
b1111111 %
1!
#130
0!
#131
b11 &
b11111110 %
1!
#132
0!
#133
b11111101 %
1!
#134
0!
#135
b11111011 %
1!
#136
0!
#137
b1001 &
b11110111 %
1!
#138
0!
#139
b11111111 &
b11101111 %
1!
#140
0!
#141
b11011111 %
1!
#142
0!
#143
b10111111 %
1!
#144
0!
#145
b1111111 %
1!
#146
0!
#147
b11 &
b11111110 %
1!
#148
0!
#149
b11111101 %
1!
#150
0!
#151
b11111011 %
1!
#152
0!
#153
b1001 &
b11110111 %
1!
#154
0!
#155
b11111111 &
b11101111 %
1!
#156
0!
#157
b11011111 %
1!
#158
0!
#159
b10111111 %
1!
#160
0!
#161
b1111111 %
1!
#162
0!
#163
b11 &
b11111110 %
1!
#164
0!
#165
b11111101 %
1!
#166
0!
#167
b11111011 %
1!
#168
0!
#169
b1001 &
b11110111 %
1!
#170
0!
#171
b11111111 &
b11101111 %
1!
#172
0!
#173
b11011111 %
1!
#174
0!
#175
b10111111 %
1!
#176
0!
#177
b1111111 %
1!
#178
0!
#179
b11 &
b11111110 %
1!
#180
0!
#181
b11111101 %
1!
#182
0!
#183
b11111011 %
1!
#184
0!
#185
b1001 &
b11110111 %
1!
#186
0!
#187
b11111111 &
b11101111 %
1!
#188
0!
#189
b11011111 %
1!
#190
0!
#191
b10111111 %
1!
#192
0!
#193
b1111111 %
1!
#194
0!
#195
b11 &
b11111110 %
1!
#196
0!
#197
b11111101 %
1!
#198
0!
#199
b11111011 %
1!
#200
0!
#201
b1001 &
b11110111 %
1!
#202
0!
#203
b11111111 &
b11101111 %
1!
#204
0!
#205
b11011111 %
1!
#206
0!
#207
b10111111 %
1!
#208
0!
#209
b1111111 %
1!
#210
0!
#211
b11 &
b11111110 %
1!
#212
0!
#213
b11111101 %
1!
#214
0!
#215
b11111011 %
1!
#216
0!
#217
b1001 &
b11110111 %
1!
0$
#218
0!
#219
b11111111 &
b11101111 %
1!
#220
0!
#221
b11011111 %
1!
#222
0!
#223
b10111111 %
1!
#224
0!
#225
b1111111 %
1!
#226
0!
#227
b11 &
b11111110 %
1!
0#
#228
0!
#229
b11111101 %
1!
#230
0!
#231
b11111011 %
1!
#232
0!
1#
#233
b1001 &
b11110111 %
1!
#234
0!
#235
b11111111 &
b11101111 %
1!
#236
0!
#237
b11011111 %
1!
0#
#238
0!
#239
b10111111 %
1!
#240
0!
#241
b1111111 %
1!
#242
0!
1$
1#
#243
b11 &
b11111110 %
1!
#244
0!
#245
b11111101 %
1!
#246
0!
#247
b11111011 %
1!
0#
#248
0!
#249
b1001 &
b11110111 %
1!
#250
0!
#251
b11111111 &
b11101111 %
1!
#252
0!
1#
#253
b11011111 %
1!
#254
0!
#255
b10111111 %
1!
#256
0!
#257
b1111111 %
1!
0#
#258
0!
#259
b11 &
b11111110 %
1!
#260
0!
#261
b11111101 %
1!
#262
0!
0$
1#
#263
b11111011 %
1!
#264
0!
#265
b1001 &
b11110111 %
1!
#266
0!
#267
b11111111 &
b11101111 %
1!
0#
#268
0!
#269
b11011111 %
1!
#270
0!
#271
b10111111 %
1!
#272
0!
1#
#273
b1111111 %
1!
#274
0!
#275
b11 &
b11111110 %
1!
#276
0!
#277
b11111101 %
1!
0#
#278
0!
#279
b11111011 %
1!
#280
0!
#281
b1001 &
b11110111 %
1!
#282
0!
1#
#283
b11111111 &
b11101111 %
1!
#284
0!
#285
b11011111 %
1!
#286
0!
#287
b10111111 %
1!
0#
#288
0!
#289
b1111111 %
1!
#290
0!
#291
b11 &
b11111110 %
1!
#292
0!
1$
1#
#293
b11111101 %
1!
#294
0!
#295
b11111011 %
1!
#296
0!
#297
b1001 &
b11110111 %
1!
0#
#298
0!
#299
b11111111 &
b11101111 %
1!
#300
0!
#301
b11011111 %
1!
#302
0!
0$
1#
#303
b10111111 %
1!
#304
0!
#305
b1111111 %
1!
#306
0!
#307
b11 &
b11111110 %
1!
0#
#308
0!
#309
b11111101 %
1!
#310
0!
#311
b11111011 %
1!
#312
0!
1$
1#
#313
b1001 &
b11110111 %
1!
#314
0!
#315
b11111111 &
b11101111 %
1!
#316
0!
#317
b11011111 %
1!
0#
#318
0!
#319
b10111111 %
1!
#320
0!
#321
b1111111 %
1!
#322
0!
1#
#323
b11 &
b11111110 %
1!
#324
0!
#325
b11111101 %
1!
#326
0!
#327
b11111011 %
1!
0#
#328
0!
#329
b1001 &
b11110111 %
1!
#330
0!
#331
b1001 (
b11111111 &
b11101111 %
1!
#332
0!
1#
#333
b11011111 %
1!
#334
0!
#335
b10111111 %
1!
#336
0!
#337
b1111111 %
1!
#338
0!
#339
b11 &
b11111110 %
1!
#340
0!
#341
b11111101 %
1!
#342
0!
#343
b1001 &
b11111011 %
1!
#344
0!
#345
b11110111 %
1!
#346
0!
#347
b11111111 &
b11101111 %
1!
#348
0!
#349
b11011111 %
1!
#350
0!
#351
b10111111 %
1!
#352
0!
#353
b1111111 %
1!
#354
0!
#355
b11 &
b11111110 %
1!
#356
0!
#357
b11111101 %
1!
#358
0!
#359
b1001 &
b11111011 %
1!
#360
0!
#361
b11110111 %
1!
#362
0!
#363
b11111111 &
b11101111 %
1!
#364
0!
#365
b11011111 %
1!
#366
0!
#367
b10111111 %
1!
#368
0!
#369
b1111111 %
1!
#370
0!
#371
b11 &
b11111110 %
1!
#372
0!
#373
b11111101 %
1!
#374
0!
#375
b1001 &
b11111011 %
1!
#376
0!
#377
b11110111 %
1!
#378
0!
#379
b11111111 &
b11101111 %
1!
#380
0!
#381
b11011111 %
1!
#382
0!
#383
b10111111 %
1!
#384
0!
#385
b1111111 %
1!
#386
0!
#387
b11 &
b11111110 %
1!
#388
0!
#389
b11111101 %
1!
#390
0!
#391
b1001 &
b11111011 %
1!
#392
0!
#393
b11110111 %
1!
#394
0!
#395
b11111111 &
b11101111 %
1!
#396
0!
#397
b11011111 %
1!
#398
0!
#399
b10111111 %
1!
#400
0!
#401
b1111111 %
1!
#402
0!
#403
b11 &
b11111110 %
1!
#404
0!
#405
b11111101 %
1!
#406
0!
#407
b1001 &
b11111011 %
1!
#408
0!
#409
b11110111 %
1!
#410
0!
#411
b11111111 &
b11101111 %
1!
#412
0!
#413
b11011111 %
1!
#414
0!
#415
b10111111 %
1!
#416
0!
#417
b1111111 %
1!
#418
0!
#419
b11 &
b11111110 %
1!
#420
0!
#421
b11111101 %
1!
#422
0!
#423
b1001 &
b11111011 %
1!
#424
0!
#425
b11110111 %
1!
#426
0!
#427
b11111111 &
b11101111 %
1!
#428
0!
#429
b11011111 %
1!
#430
0!
#431
b10111111 %
1!
#432
0!
0$
#433
b1111111 %
1!
#434
0!
#435
b11 &
b11111110 %
1!
#436
0!
#437
b11111101 %
1!
#438
0!
#439
b1001 &
b11111011 %
1!
#440
0!
#441
b11110111 %
1!
#442
0!
0#
#443
b11111111 &
b11101111 %
1!
#444
0!
#445
b11011111 %
1!
#446
0!
#447
b10111111 %
1!
1#
#448
0!
#449
b1111111 %
1!
#450
0!
#451
b11 &
b11111110 %
1!
#452
0!
0#
#453
b11111101 %
1!
#454
0!
#455
b1001 &
b11111011 %
1!
#456
0!
#457
b11110111 %
1!
1$
1#
#458
0!
#459
b11111111 &
b11101111 %
1!
#460
0!
#461
b11011111 %
1!
#462
0!
0#
#463
b10111111 %
1!
#464
0!
#465
b1111111 %
1!
#466
0!
#467
b11 &
b11111110 %
1!
1#
#468
0!
#469
b11111101 %
1!
#470
0!
#471
b1001 &
b11111011 %
1!
#472
0!
0#
#473
b11110111 %
1!
#474
0!
#475
b11111111 &
b11101111 %
1!
#476
0!
#477
b11011111 %
1!
0$
1#
#478
0!
#479
b10111111 %
1!
#480
0!
#481
b1111111 %
1!
#482
0!
0#
#483
b11 &
b11111110 %
1!
#484
0!
#485
b11111101 %
1!
#486
0!
#487
b1001 &
b11111011 %
1!
1$
1#
#488
0!
#489
b11110111 %
1!
#490
0!
#491
b11111111 &
b11101111 %
1!
#492
0!
0#
#493
b11011111 %
1!
#494
0!
#495
b10111111 %
1!
#496
0!
#497
b1111111 %
1!
0$
1#
#498
0!
#499
b11 &
b11111110 %
1!
#500
0!
#501
b11111101 %
1!
#502
0!
0#
#503
b1001 &
b11111011 %
1!
#504
0!
#505
b11110111 %
1!
#506
0!
#507
b11111111 &
b11101111 %
1!
1#
#508
0!
#509
b11011111 %
1!
#510
0!
#511
b10111111 %
1!
#512
0!
0#
#513
b1111111 %
1!
#514
0!
#515
b11 &
b11111110 %
1!
#516
0!
#517
b11111101 %
1!
1#
#518
0!
#519
b1001 &
b11111011 %
1!
#520
0!
#521
b11110111 %
1!
#522
0!
0#
#523
b11111111 &
b11101111 %
1!
#524
0!
#525
b11011111 %
1!
#526
0!
#527
b10111111 %
1!
1$
1#
#528
0!
#529
b1111111 %
1!
#530
0!
#531
b11 &
b11111110 %
1!
#532
0!
0#
#533
b11111101 %
1!
#534
0!
#535
b1001 &
b11111011 %
1!
#536
0!
#537
b11110111 %
1!
1#
#538
0!
#539
b11111111 &
b11101111 %
1!
#540
0!
#541
b11011111 %
1!
#542
0!
0#
#543
b10111111 %
1!
#544
0!
#545
b1111111 %
1!
#546
0!
#547
b1 '
b1001 )
b11 &
b11111110 %
1!
1#
#548
0!
#549
b1001 &
b11111101 %
1!
#550
0!
#551
b11111011 %
1!
#552
0!
#553
b10011111 &
b11110111 %
1!
#554
0!
#555
b11111111 &
b11101111 %
1!
#556
0!
#557
b11011111 %
1!
#558
0!
#559
b10111111 %
1!
#560
0!
#561
b1111111 %
1!
#562
0!
#563
b11 &
b11111110 %
1!
#564
0!
#565
b1001 &
b11111101 %
1!
#566
0!
#567
b11111011 %
1!
#568
0!
#569
b10011111 &
b11110111 %
1!
#570
0!
#571
b11111111 &
b11101111 %
1!
#572
0!
#573
b11011111 %
1!
#574
0!
#575
b10111111 %
1!
#576
0!
#577
b1111111 %
1!
#578
0!
#579
b11 &
b11111110 %
1!
#580
0!
#581
b1001 &
b11111101 %
1!
#582
0!
#583
b11111011 %
1!
#584
0!
#585
b10011111 &
b11110111 %
1!
#586
0!
#587
b11111111 &
b11101111 %
1!
#588
0!
#589
b11011111 %
1!
#590
0!
#591
b10111111 %
1!
#592
0!
#593
b1111111 %
1!
#594
0!
#595
b11 &
b11111110 %
1!
#596
0!
#597
b1001 &
b11111101 %
1!
#598
0!
#599
b11111011 %
1!
#600
0!
#601
b10011111 &
b11110111 %
1!
#602
0!
#603
b11111111 &
b11101111 %
1!
#604
0!
#605
b11011111 %
1!
#606
0!
#607
b10111111 %
1!
#608
0!
#609
b1111111 %
1!
#610
0!
#611
b11 &
b11111110 %
1!
#612
0!
#613
b1001 &
b11111101 %
1!
#614
0!
#615
b11111011 %
1!
#616
0!
#617
b10011111 &
b11110111 %
1!
#618
0!
#619
b11111111 &
b11101111 %
1!
#620
0!
#621
b11011111 %
1!
#622
0!
#623
b10111111 %
1!
#624
0!
#625
b1111111 %
1!
#626
0!
#627
b11 &
b11111110 %
1!
#628
0!
#629
b1001 &
b11111101 %
1!
#630
0!
#631
b11111011 %
1!
#632
0!
#633
b10011111 &
b11110111 %
1!
#634
0!
#635
b11111111 &
b11101111 %
1!
#636
0!
#637
b11011111 %
1!
#638
0!
#639
b10111111 %
1!
#640
0!
#641
b1111111 %
1!
#642
0!
#643
b11 &
b11111110 %
1!
#644
0!
#645
b1001 &
b11111101 %
1!
#646
0!
#647
b11111011 %
1!
0$
#648
0!
#649
b10011111 &
b11110111 %
1!
#650
0!
#651
b11111111 &
b11101111 %
1!
#652
0!
#653
b11011111 %
1!
#654
0!
#655
b10111111 %
1!
#656
0!
#657
b1111111 %
1!
0#
#658
0!
#659
b11 &
b11111110 %
1!
#660
0!
#661
b1001 &
b11111101 %
1!
#662
0!
1$
1#
#663
b11111011 %
1!
#664
0!
#665
b10011111 &
b11110111 %
1!
#666
0!
#667
b11111111 &
b11101111 %
1!
0#
#668
0!
#669
b11011111 %
1!
#670
0!
#671
b10111111 %
1!
#672
0!
1#
#673
b1111111 %
1!
#674
0!
#675
b11 &
b11111110 %
1!
#676
0!
#677
b1001 &
b11111101 %
1!
0#
#678
0!
#679
b11111011 %
1!
#680
0!
#681
b10011111 &
b11110111 %
1!
#682
0!
0$
1#
#683
b11111111 &
b11101111 %
1!
#684
0!
#685
b11011111 %
1!
#686
0!
#687
b10111111 %
1!
0#
#688
0!
#689
b1111111 %
1!
#690
0!
#691
b11 &
b11111110 %
1!
#692
0!
1$
1#
#693
b1001 &
b11111101 %
1!
#694
0!
#695
b11111011 %
1!
#696
0!
#697
b10011111 &
b11110111 %
1!
0#
#698
0!
#699
b11111111 &
b11101111 %
1!
#700
0!
#701
b11011111 %
1!
#702
0!
1#
#703
b10111111 %
1!
#704
0!
#705
b1111111 %
1!
#706
0!
#707
b11 &
b11111110 %
1!
0#
#708
0!
#709
b1001 &
b11111101 %
1!
#710
0!
#711
b11111011 %
1!
#712
0!
1#
#713
b10011111 &
b11110111 %
1!
#714
0!
#715
b11111111 &
b11101111 %
1!
#716
0!
#717
b11011111 %
1!
0#
#718
0!
#719
b10111111 %
1!
#720
0!
#721
b1111111 %
1!
#722
0!
1#
#723
b11 &
b11111110 %
1!
#724
0!
#725
b1001 &
b11111101 %
1!
#726
0!
#727
b11111011 %
1!
0#
#728
0!
#729
b10011111 &
b11110111 %
1!
#730
0!
#731
b11111111 &
b11101111 %
1!
#732
0!
0$
1#
#733
b11011111 %
1!
#734
0!
#735
b10111111 %
1!
#736
0!
#737
b1111111 %
1!
0#
#738
0!
#739
b11 &
b11111110 %
1!
#740
0!
#741
b1001 &
b11111101 %
1!
#742
0!
1#
#743
b11111011 %
1!
#744
0!
#745
b10011111 &
b11110111 %
1!
#746
0!
#747
b11111111 &
b11101111 %
1!
0#
#748
0!
#749
b11011111 %
1!
#750
0!
#751
b10111111 %
1!
#752
0!
1$
1#
#753
b1111111 %
1!
#754
0!
#755
b11 &
b11111110 %
1!
#756
0!
#757
b1001 &
b11111101 %
1!
0#
#758
0!
#759
b11111011 %
1!
#760
0!
#761
b10011111 &
b11110111 %
1!
#762
0!
1#
#763
b11111111 &
b11101111 %
1!
#764
0!
#765
b11011111 %
1!
#766
0!
#767
b10111111 %
1!
#768
0!
#769
b1111111 %
1!
#770
0!
#771
b11 &
b11111110 %
1!
#772
0!
#773
b1001 &
b11111101 %
1!
#774
0!
#775
b11111011 %
1!
#776
0!
#777
b10011111 &
b11110111 %
1!
#778
0!
#779
b11111111 &
b11101111 %
1!
#780
0!
#781
b11011111 %
1!
#782
0!
#783
b10111111 %
1!
#784
0!
#785
b1111111 %
1!
#786
0!
#787
b11 &
b11111110 %
1!
#788
0!
#789
b1001 &
b11111101 %
1!
#790
0!
#791
b11111011 %
1!
#792
0!
#793
b10011111 &
b11110111 %
1!
#794
0!
#795
b11111111 &
b11101111 %
1!
#796
0!
#797
b11011111 %
1!
#798
0!
#799
b10111111 %
1!
#800
0!
#801
b1111111 %
1!
#802
0!
#803
b11 &
b11111110 %
1!
#804
0!
#805
b1001 &
b11111101 %
1!
#806
0!
#807
b11111011 %
1!
#808
0!
#809
b10011111 &
b11110111 %
1!
#810
0!
#811
b11111111 &
b11101111 %
1!
#812
0!
#813
b11011111 %
1!
#814
0!
#815
b10111111 %
1!
#816
0!
#817
b1111111 %
1!
#818
0!
#819
b11 &
b11111110 %
1!
#820
0!
#821
b1001 &
b11111101 %
1!
#822
0!
#823
b11111011 %
1!
#824
0!
#825
b10011111 &
b11110111 %
1!
#826
0!
#827
b11111111 &
b11101111 %
1!
#828
0!
#829
b11011111 %
1!
#830
0!
#831
b10111111 %
1!
#832
0!
#833
b1111111 %
1!
#834
0!
#835
b11 &
b11111110 %
1!
#836
0!
#837
b1001 &
b11111101 %
1!
#838
0!
#839
b11111011 %
1!
#840
0!
#841
b10011111 &
b11110111 %
1!
#842
0!
#843
b11111111 &
b11101111 %
1!
#844
0!
#845
b11011111 %
1!
#846
0!
#847
b10111111 %
1!
#848
0!
#849
b1111111 %
1!
#850
0!
#851
b11 &
b11111110 %
1!
#852
0!
#853
b1001 &
b11111101 %
1!
#854
0!
#855
b11111011 %
1!
#856
0!
#857
b10011111 &
b11110111 %
1!
#858
0!
#859
b11111111 &
b11101111 %
1!
#860
0!
#861
b11011111 %
1!
#862
0!
0$
#863
b10111111 %
1!
#864
0!
#865
b1111111 %
1!
#866
0!
#867
b11 &
b11111110 %
1!
#868
0!
#869
b1001 &
b11111101 %
1!
#870
0!
#871
b11111011 %
1!
#872
0!
0#
#873
b10011111 &
b11110111 %
1!
#874
0!
#875
b11111111 &
b11101111 %
1!
#876
0!
#877
b11011111 %
1!
1#
#878
0!
